schemallama_types/__init__.py
schemallama_types/py.typed
schemallama_types/assets/__init__.py
schemallama_types/assets/wrapper.py
londonaicentre_schemallama_types-1.0.0.dist-info/METADATA
londonaicentre_schemallama_types-1.0.0.dist-info/WHEEL
londonaicentre_schemallama_types-1.0.0.dist-info/top_level.txt
londonaicentre_schemallama_types-1.0.0.dist-info/RECORD
